whatifact/__init__.py
whatifact/_inference.py
whatifact/_server.py
whatifact/_utilities.py
whatifact/_widgets.py
whatifact/whatifact.py
whatifact/resources/revert_icon.svg
whatifact/resources/style.css
whatifact-0.1.6.dist-info/LICENSE
whatifact-0.1.6.dist-info/METADATA
whatifact-0.1.6.dist-info/WHEEL
whatifact-0.1.6.dist-info/top_level.txt
whatifact-0.1.6.dist-info/RECORD
