Metadata-Version: 2.2
Name: whatifact
Version: 0.1.6
Summary: Counter factual exploration utility
Home-page: http://github.com/urigott/whatifact
Author-email: Uri Gottlieb <urigott@gmail.com>
License: MIT License
Requires-Python: >=3.9
License-File: LICENSE
Requires-Dist: numpy>=1.26.0
Requires-Dist: pandas>=1.1.0
Requires-Dist: shiny>=1.0.0
Dynamic: home-page
